mloda_plugin_template-0.2.2.dist-info/licenses/LICENSE
placeholder/__init__.py
placeholder/compute_frameworks/__init__.py
placeholder/compute_frameworks/my_plugin/__init__.py
placeholder/compute_frameworks/my_plugin/my_compute_framework.py
placeholder/compute_frameworks/my_plugin/tests/__init__.py
placeholder/compute_frameworks/my_plugin/tests/test_my_compute_framework.py
placeholder/extenders/__init__.py
placeholder/extenders/my_plugin/__init__.py
placeholder/extenders/my_plugin/my_extender.py
placeholder/extenders/my_plugin/tests/__init__.py
placeholder/extenders/my_plugin/tests/test_my_extender.py
placeholder/feature_groups/__init__.py
placeholder/feature_groups/my_plugin/__init__.py
placeholder/feature_groups/my_plugin/my_feature_group.py
placeholder/feature_groups/my_plugin/tests/__init__.py
placeholder/feature_groups/my_plugin/tests/test_my_feature_group.py
mloda_plugin_template-0.2.2.dist-info/METADATA
mloda_plugin_template-0.2.2.dist-info/WHEEL
mloda_plugin_template-0.2.2.dist-info/top_level.txt
mloda_plugin_template-0.2.2.dist-info/RECORD
