Metadata-Version: 2.4
Name: mloda-plugin-template
Version: 0.2.2
Summary: TEMPLATE PLACEHOLDER - Do not install directly. This package reserves the name for mloda-plugin-template. See https://github.com/mloda-ai/mloda-plugin-template
Author-email: mloda-ai <info@mloda.ai>
License-Expression: Apache-2.0
Requires-Python: >=3.10
License-File: LICENSE
Requires-Dist: mloda>=0.4.3
Requires-Dist: mloda-testing>=0.2.6
Provides-Extra: dev
Requires-Dist: tox; extra == "dev"
Requires-Dist: tox-uv; extra == "dev"
Requires-Dist: pytest; extra == "dev"
Requires-Dist: ruff; extra == "dev"
Requires-Dist: mypy; extra == "dev"
Requires-Dist: bandit; extra == "dev"
Dynamic: license-file
